MANIFEST.in
README.rst
setup.py
docs/conf.py
docs/index.rst
xbob/__init__.py
xbob.db.nuaa.egg-info/PKG-INFO
xbob.db.nuaa.egg-info/SOURCES.txt
xbob.db.nuaa.egg-info/dependency_links.txt
xbob.db.nuaa.egg-info/entry_points.txt
xbob.db.nuaa.egg-info/namespace_packages.txt
xbob.db.nuaa.egg-info/not-zip-safe
xbob.db.nuaa.egg-info/requires.txt
xbob.db.nuaa.egg-info/top_level.txt
xbob/db/__init__.py
xbob/db/nuaa/__init__.py
xbob/db/nuaa/driver.py
xbob/db/nuaa/models.py
xbob/db/nuaa/test.py
xbob/db/nuaa/Detectedface/client_test_face.txt
xbob/db/nuaa/Detectedface/client_train_face.txt
xbob/db/nuaa/Detectedface/imposter_test_face.txt
xbob/db/nuaa/Detectedface/imposter_train_face.txt
xbob/db/nuaa/NormalizedFace/client_test_normalized.txt
xbob/db/nuaa/NormalizedFace/client_train_normalized.txt
xbob/db/nuaa/NormalizedFace/imposter_test_normalized.txt
xbob/db/nuaa/NormalizedFace/imposter_train_normalized.txt
xbob/db/nuaa/folds/cross_valid.txt
xbob/db/nuaa/folds/detected_face_attack.txt
xbob/db/nuaa/folds/detected_face_real.txt
xbob/db/nuaa/folds/normalized_face_attack.txt
xbob/db/nuaa/folds/normalized_face_real.txt
xbob/db/nuaa/folds/raw_attack.txt
xbob/db/nuaa/folds/raw_real.txt
xbob/db/nuaa/raw/client_test_raw.txt
xbob/db/nuaa/raw/client_train_raw.txt
xbob/db/nuaa/raw/imposter_test_raw.txt
xbob/db/nuaa/raw/imposter_train_raw.txt