Metadata-Version: 1.1
Name: xbob.db.nuaa
Version: 1.0.2
Summary: NUAA Face Spoofing Attack Database Access API for Bob
Home-page: http://pypi.python.org/pypi/xbob.db.nuaa
Author: Andre Anjos
Author-email: andre.anjos@idiap.ch
License: GPLv3
Platform: UNKNOWN
Classifier: Development Status :: 4 - Beta
Classifier: Intended Audience :: Developers
Classifier: License :: OSI Approved :: GNU General Public License v3 (GPLv3)
Classifier: Natural Language :: English
Classifier: Programming Language :: Python
Classifier: Topic :: Scientific/Engineering :: Artificial Intelligence
Classifier: Topic :: Database :: Front-Ends
